rynn/__init__.py
rynn/dataloaders.py
rynn/models.py
rynn/predictor.py
rynn/schedulers.py
rynn/setup.py
rynn/trainer.py
rynn/types.py
rynn/utils.py
rynn-0.0.1a1.dist-info/METADATA
rynn-0.0.1a1.dist-info/WHEEL
rynn-0.0.1a1.dist-info/entry_points.txt
rynn-0.0.1a1.dist-info/RECORD
